sreegcloud.py
sreegcloud-2.0.0.dist-info/LICENSE
sreegcloud-2.0.0.dist-info/METADATA
sreegcloud-2.0.0.dist-info/WHEEL
sreegcloud-2.0.0.dist-info/top_level.txt
sreegcloud-2.0.0.dist-info/RECORD
