Metadata-Version: 2.1
Name: sreegcloud
Version: 2.0.0
Summary: Quicksample Test Package for SQLShack Demo
Home-page: UNKNOWN
Author: Aveek Das
License: UNKNOWN
Platform: UNKNOWN
Classifier: Programming Language :: Python :: 3
Classifier: License :: OSI Approved :: MIT License
Classifier: Operating System :: OS Independent
Requires-Python: >=3.6
License-File: LICENSE
